LICENSE
README.md
setup.py
freelancer/__init__.py
freelancer/api.py
freelancer/cli.py
freelancer/client.py
freelancer/oauth.py
freelancer/response.py
freelancer.egg-info/PKG-INFO
freelancer.egg-info/SOURCES.txt
freelancer.egg-info/dependency_links.txt
freelancer.egg-info/entry_points.txt
freelancer.egg-info/requires.txt
freelancer.egg-info/top_level.txt
tests/
tests/test_freelancer.py