Metadata-Version: 1.0
Name: freelancer
Version: 0.2.1
Summary: API Library for freelancer.com
Home-page: http://github.com/ecooper/python-freelancer
Author: E. Cooper
Author-email: strangerthanus@gmail.com
License: GNU General Public License v3
Platform: UNKNOWN
